jupyterlab_pygments/__init__.py
jupyterlab_pygments/_version.py
jupyterlab_pygments/style.py
jupyterlab_pygments/labextension/package.json
jupyterlab_pygments/labextension/static/568.1e2faa2ba0bbe59c4780.js
jupyterlab_pygments/labextension/static/747.8eb3ddccc7ec4987bff9.js
jupyterlab_pygments/labextension/static/remoteEntry.aa1060b2d1221f8e5688.js
jupyterlab_pygments/labextension/static/style.js
jupyterlab_pygments/labextension/static/third-party-licenses.json
jupyterlab_pygments-0.2.2.data/data/share/jupyter/labextensions/jupyterlab_pygments/install.json
jupyterlab_pygments-0.2.2.data/data/share/jupyter/labextensions/jupyterlab_pygments/package.json
jupyterlab_pygments-0.2.2.data/data/share/jupyter/labextensions/jupyterlab_pygments/static/568.1e2faa2ba0bbe59c4780.js
jupyterlab_pygments-0.2.2.data/data/share/jupyter/labextensions/jupyterlab_pygments/static/747.8eb3ddccc7ec4987bff9.js
jupyterlab_pygments-0.2.2.data/data/share/jupyter/labextensions/jupyterlab_pygments/static/remoteEntry.aa1060b2d1221f8e5688.js
jupyterlab_pygments-0.2.2.data/data/share/jupyter/labextensions/jupyterlab_pygments/static/style.js
jupyterlab_pygments-0.2.2.data/data/share/jupyter/labextensions/jupyterlab_pygments/static/third-party-licenses.json
jupyterlab_pygments-0.2.2.dist-info/LICENSE
jupyterlab_pygments-0.2.2.dist-info/METADATA
jupyterlab_pygments-0.2.2.dist-info/WHEEL
jupyterlab_pygments-0.2.2.dist-info/top_level.txt
jupyterlab_pygments-0.2.2.dist-info/RECORD
