Metadata-Version: 2.1
Name: jupyterlab_pygments
Version: 0.2.2
Summary: Pygments theme using JupyterLab CSS variables
Home-page: https://github.com/jupyterlab/jupyterlab_pygments
Author: Jupyter Development Team
Author-email: jupyter@googlegroups.com
License: BSD
Keywords: jupyter,jupyterlab,JupyterLab3,pygments
Platform: UNKNOWN
Requires-Python: >=3.7
License-File: LICENSE
